python_ci_template/__init__.py
python_ci_template/console.py
python_ci_template-0.1.1.dist-info/entry_points.txt
python_ci_template-0.1.1.dist-info/LICENSE
python_ci_template-0.1.1.dist-info/WHEEL
python_ci_template-0.1.1.dist-info/METADATA
python_ci_template-0.1.1.dist-info/RECORD
