Metadata-Version: 2.1
Name: python-ci-template
Version: 0.1.1
Summary: template to create python package including generic CI tools
License: MIT
Author: dolfno
Author-email: dnoordman@schubergphilis.com
Requires-Python: >=3.9,<3.10
Classifier: License :: OSI Approved :: MIT License
Classifier: Programming Language :: Python :: 3
Classifier: Programming Language :: Python :: 3.9
Requires-Dist: awswrangler (>=2.12.1,<3.0.0)
Requires-Dist: click (>=8.0.3,<9.0.0)
Requires-Dist: desert (>=2020.11.18,<2021.0.0)
